textual_tags/__init__.py
textual_tags/demo.py
textual_tags/flexbox.py
textual_tags/assets/demo.tcss
textual_tags-0.3.3.dist-info/METADATA
textual_tags-0.3.3.dist-info/WHEEL
textual_tags-0.3.3.dist-info/entry_points.txt
textual_tags-0.3.3.dist-info/RECORD
