Metadata-Version: 2.4
Name: textual-tags
Version: 0.3.3
Summary: A custom tags widget to be used in textual applications
Project-URL: Repository, https://github.com/Zaloog/textual-tags
Project-URL: Changelog, https://github.com/Zaloog/textual-tags/blob/main/CHANGELOG.md
Author-email: Zaloog <gramslars@gmail.com>
License: MIT
Keywords: python,tags,textual,tui,uv
Classifier: Development Status :: 3 - Alpha
Classifier: License :: OSI Approved :: MIT License
Classifier: Operating System :: OS Independent
Classifier: Programming Language :: Python
Classifier: Programming Language :: Python :: 3 :: Only
Classifier: Programming Language :: Python :: 3.10
Classifier: Programming Language :: Python :: 3.11
Classifier: Programming Language :: Python :: 3.12
Classifier: Programming Language :: Python :: 3.13
Requires-Python: >=3.10
Requires-Dist: textual-autocomplete>=4.0.4
Requires-Dist: textual>=3.1.0
